minio_file/__init__.py
minio_file/minio_file.py
surfdrive/__init__.py
surfdrive/surfdrive_download.py
sdp_tools-2025.1.10.dist-info/METADATA
sdp_tools-2025.1.10.dist-info/WHEEL
sdp_tools-2025.1.10.dist-info/entry_points.txt
sdp_tools-2025.1.10.dist-info/licenses/LICENSE
sdp_tools-2025.1.10.dist-info/RECORD
