Metadata-Version: 2.4
Name: sdp-tools
Version: 2025.1.10
Summary: Tool to manage MinIO connections and transfers.
Project-URL: Homepage, https://github.com/cedanl/sdp-tools
Project-URL: Repository, https://github.com/cedanl/sdp-tools
Project-URL: Issues, https://github.com/cedanl/sdp-tools/issues
Author-email: Caspar Nijhuis <caspar.nijhuis@gmail.com>
License: MIT
License-File: LICENSE
Classifier: Development Status :: 2 - Pre-Alpha
Classifier: Intended Audience :: Developers
Classifier: License :: OSI Approved :: MIT License
Classifier: Natural Language :: English
Classifier: Programming Language :: Python :: 3
Classifier: Programming Language :: Python :: 3.9
Classifier: Programming Language :: Python :: 3.10
Classifier: Programming Language :: Python :: 3.11
Classifier: Programming Language :: Python :: 3.12
Classifier: Programming Language :: Python :: 3.13
Requires-Python: >=3.9
Requires-Dist: minio>=7.0.0
Requires-Dist: pandas>=2.0.0
Requires-Dist: requests>=2.31.0
Provides-Extra: dev
Requires-Dist: black>=23.12.1; extra == 'dev'
Requires-Dist: bump-my-version>=0.15.4; extra == 'dev'
Requires-Dist: flake8-docstrings>=1.7.0; extra == 'dev'
Requires-Dist: flake8>=6.1.0; extra == 'dev'
Requires-Dist: isort>=5.13.2; extra == 'dev'
Requires-Dist: mkdocs-autorefs>=0.5.0; extra == 'dev'
Requires-Dist: mkdocs-include-markdown-plugin>=6.0.4; extra == 'dev'
Requires-Dist: mkdocs-material-extensions>=1.3.1; extra == 'dev'
Requires-Dist: mkdocs-material>=9.5.2; extra == 'dev'
Requires-Dist: mkdocs>=1.5.3; extra == 'dev'
Requires-Dist: mypy>=1.8.0; extra == 'dev'
Requires-Dist: pandas-stubs>=2.2; extra == 'dev'
Requires-Dist: pre-commit>=3.6.0; extra == 'dev'
Requires-Dist: pytest-cov>=4.1.0; extra == 'dev'
Requires-Dist: pytest-mock>=3.10.0; extra == 'dev'
Requires-Dist: pytest>=7.4.3; extra == 'dev'
Requires-Dist: toml>=0.10.2; extra == 'dev'
Requires-Dist: tox>=4.11.4; extra == 'dev'
Requires-Dist: twine>=4.0.2; extra == 'dev'
Provides-Extra: test
Requires-Dist: pytest-cov>=4.1.0; extra == 'test'
Requires-Dist: pytest-mock>=3.10.0; extra == 'test'
Requires-Dist: pytest>=7.4.3; extra == 'test'
Requires-Dist: tomli>=2.0.0; (python_version < '3.11') and extra == 'test'
